<?xml version="1.0" encoding="utf-8" ?>
<odoo>
    <record id="serviciogser2_view_form" model="ir.ui.view">
        <field name="name">serviciogser2.view.form</field>
        <field name="model">project.project</field>
        <field name="inherit_id" ref="project.view_task_form2"></field>
        <field name="arch" type="xml">
        <field name="partner_id" position="after">
          <field name="datop" />
        </field>
         <!--page name="description" position="after">
            <group string="Ruta">
              <group>
                <group string="Ruta">
                </group>
              </group>
            </group>
          </page-->
        </field>
    </record>


     

</odoo>